carbonplan_styles/__init__.py
carbonplan_styles/altair.py
carbonplan_styles/colors.py
carbonplan_styles/data/colormaps.json
carbonplan_styles/mpl/__init__.py
carbonplan_styles/mpl/colormaps.py
carbonplan_styles/tests/test_altair.py
carbonplan_styles/tests/test_mpl.py
carbonplan_styles-0.5.1.dist-info/LICENSE
carbonplan_styles-0.5.1.dist-info/METADATA
carbonplan_styles-0.5.1.dist-info/WHEEL
carbonplan_styles-0.5.1.dist-info/entry_points.txt
carbonplan_styles-0.5.1.dist-info/top_level.txt
carbonplan_styles-0.5.1.dist-info/RECORD
