Metadata-Version: 2.1
Name: carbonplan-styles
Version: 0.5.1
Summary: CarbonPlan plotting styles
Author-email: CarbonPlan <tech@carbonplan.org>
License: MIT
Project-URL: repository, https://github.com/carbonplan/style
Keywords: matplotlib,altair
Classifier: Development Status :: 2 - Pre-Alpha
Classifier: License :: OSI Approved :: MIT License
Classifier: Operating System :: OS Independent
Classifier: Intended Audience :: Science/Research
Classifier: Programming Language :: Python
Classifier: Programming Language :: Python :: 3
Classifier: Programming Language :: Python :: 3.10
Classifier: Programming Language :: Python :: 3.11
Classifier: Programming Language :: Python :: 3.12
Classifier: Topic :: Scientific/Engineering
Requires-Python: >=3.10
License-File: LICENSE
Requires-Dist: altair
Requires-Dist: carbonplan
Requires-Dist: matplotlib
Requires-Dist: seaborn
Provides-Extra: dev
Requires-Dist: pytest ; extra == 'dev'
Requires-Dist: pytest-sugar ; extra == 'dev'
Requires-Dist: pytest-cov ; extra == 'dev'
